{
  "appMinimumWidth": "320px",
  "breakpoints": {
    "horizontal": {
      "s": "600px",
      "m": "800px",
      "l": "1200px",
      "xl": "1600px"
    }
  },
  "button-border": "1px",
  "button-padding-top": "8px",
  "button-padding-right": "24px",
  "button-padding-bottom": "8px",
  "button-padding-left": "24px",
  "componentMargin": {
    "s": "16px",
    "m": "32px",
    "l": "60px",
    "xl": "72px"
  },
  "componentPadding": {
    "none": "0",
    "s": "12px",
    "m": "16px",
    "l": "18px",
    "xl": "24px"
  },
  "componentPaddingL": {
    "s": "18px",
    "m": "24px",
    "l": "32px",
    "xl": "40px"
  },
  "componentPaddingXl": {
    "s": "32px",
    "m": "48px",
    "l": "60px",
    "xl": "72px"
  },
  "icons": {
    "s": "16px",
    "m": "24px",
    "l": "32px",
    "xl": "48px"
  },
  "linkBorder": "3px",
  "maxSiteWidth": "1200px",
  "maxTextWidth": "850px",
  "menuWidth": "320px",
  "navButtonOffset": "24px",
  "navButtonOffsetSmall": "12px",
  "sitePadding": {
    "s": "12px",
    "m": "32px",
    "l": "60px",
    "xl": "72px"
  },
  "sectionHeadingBorder": "3px",
  "shadowDistance": {
    "large": "40px"
  },
  "touchTarget": "44px",
  "zIndex": {
    "header": "9",
    "nav": "99",
    "modal": "999"
  }
}
